gittify/__init__.py
gittify/create.py
gittify/delete.py
gittify/main.py
gittify/read.py
gittify/update.py
gittify/client/__init__.py
gittify/client/class_module.py
gittify/client/initialize.py
gittify/colors/__init__.py
gittify/colors/class_module.py
gittify/colors/initialize.py
gittify/errors/__init__.py
gittify/errors/class_module.py
gittify/errors/initialize.py
gittify/monitor/__init__.py
gittify/monitor/continuous_script.py
gittify/monitor/install.py
gittify/monitor/install_service.py
gittify/monitor/main.py
gittify/monitor/utils/__init__.py
gittify/monitor/utils/check_os.py
gittify/monitor/utils/check_service.py
gittify/utils/__init__.py
gittify/utils/check_authentic.py
gittify/utils/check_os.py
gittify/utils/clean_url.py
gittify/utils/logs.py
gittify/utils/shell_icons.py
gittify/utils/templates.py
gittify-0.1.0.dist-info/METADATA
gittify-0.1.0.dist-info/WHEEL
gittify-0.1.0.dist-info/top_level.txt
gittify-0.1.0.dist-info/RECORD
